__init__.py
block_to_generator.py
generator.py
music_models.py
note_timing.py
sample_markov.py
song_generator.py
soundfont_test.py
template_utils.py
ninopianino/__init__.py
ninopianino/block_to_generator.py
ninopianino/generator.py
ninopianino/music_models.py
ninopianino/note_timing.py
ninopianino/song_generator.py
ninopianino/template_utils.py
ninopianino-0.1.0.data/scripts/pianize
ninopianino-0.1.0.dist-info/DESCRIPTION.rst
ninopianino-0.1.0.dist-info/METADATA
ninopianino-0.1.0.dist-info/RECORD
ninopianino-0.1.0.dist-info/WHEEL
ninopianino-0.1.0.dist-info/metadata.json
ninopianino-0.1.0.dist-info/top_level.txt
