Metadata-Version: 2.0
Name: ninopianino
Version: 0.1.0
Summary: Programmable music generator. 
Home-page: https://github.com/NinoDoko/nino_pianino
Author: Nikola Dokoski
Author-email: ninodokoskiot@hotmail.com
License: UNKNOWN
Download-URL: https://github.com/NinoDoko/nino_pianino/tarball/0.1
Platform: UNKNOWN
Requires-Dist: midiutil
Requires-Dist: pyhaikunator
